speaker_diarization_pyn/SpeakerDiarization.py
speaker_diarization_pyn/__init__.py
speaker_diarization_pyaudio-0.0.2.dist-info/LICENSE.txt
speaker_diarization_pyaudio-0.0.2.dist-info/METADATA
speaker_diarization_pyaudio-0.0.2.dist-info/WHEEL
speaker_diarization_pyaudio-0.0.2.dist-info/top_level.txt
speaker_diarization_pyaudio-0.0.2.dist-info/RECORD
