Metadata-Version: 2.1
Name: speaker-diarization-pyaudio
Version: 0.0.2
Summary: A speaker diarization pipeline made with pyannote
Home-page: https://github.com/faith-nchifor/sd_pyannote
Author: FaithN
Author-email: faithnchifor@gmail.com
License: MIT
Requires-Python: >=3.8
License-File: LICENSE.txt
Requires-Dist: whisper
Requires-Dist: torch
Requires-Dist: pyannote.audio
Requires-Dist: einops
Requires-Dist: numpy
Requires-Dist: huggingface-hub
